{"assets/background_intellici.png":["assets/background_intellici.png"],"assets/bago_background.png":["assets/bago_background.png"],"assets/bago_icon.png":["assets/bago_icon.png"],"assets/bagonew.png":["assets/bagonew.png"],"assets/intellici_icon.png":["assets/intellici_icon.png"],"assets/intellici_icon2.png":["assets/intellici_icon2.png"],"assets/xingweizhunze1.jpg":["assets/xingweizhunze1.jpg"],"packages/cupertino_icons/assets/CupertinoIcons.ttf":["packages/cupertino_icons/assets/CupertinoIcons.ttf"]}